tree_sitter_haskell/__init__.py
tree_sitter_haskell/__init__.pyi
tree_sitter_haskell/_binding.pyd
tree_sitter_haskell/binding.c
tree_sitter_haskell/py.typed
tree_sitter_haskell/queries/highlights.scm
tree_sitter_haskell/queries/injections.scm
tree_sitter_haskell/queries/locals.scm
tree_sitter_haskell-0.23.1.dist-info/LICENSE
tree_sitter_haskell-0.23.1.dist-info/METADATA
tree_sitter_haskell-0.23.1.dist-info/WHEEL
tree_sitter_haskell-0.23.1.dist-info/top_level.txt
tree_sitter_haskell-0.23.1.dist-info/RECORD
